{
  "projects": [
    {
      "id": 1,
      "name": "Short-term goals"
    },
    {
      "id": 2,
      "name": "Long-term goals"
    }
  ],
  "tasks": [
    {
      "title": "Learn Redux",
      "description": "The store, actions, and reducers, oh my!!!",
      "status": "Completed",
      "timer": 153,
      "id": 1,
      "projectId": 1
    },
    {
      "title": "Peace on Earth",
      "description": "No big deal...!!!",
      "status": "Unstarted",
      "timer": 80,
      "id": 2,
      "projectId": 2
    },
    {
      "title": "",
      "description": "",
      "status": "Unstarted",
      "timer": 0,
      "id": 5
    },
    {
      "title": "",
      "description": "",
      "status": "Unstarted",
      "timer": 0,
      "id": 6
    },
    {
      "title": "Create Facebook for doges",
      "description": "The gooddest social network ever!!",
      "status": "Completed",
      "timer": 47,
      "projectId": 2,
      "id": 7
    }
  ]
}